{
  "mapMarkers": [
    {
      "id": "leaflet-map",
      "lastAccessed": 1682809757488,
      "markers": [
        {
          "id": "ID_cab99988bb0a",
          "type": "alps",
          "loc": [
            -1.0567626953125,
            1.39306640625
          ],
          "layer": "%5B%5BIMG_0117.png%5D%5D",
          "mutable": true,
          "command": false,
          "percent": null,
          "description": null,
          "minZoom": null,
          "maxZoom": null,
          "tooltip": "hover"
        },
        {
          "id": "ID_39bac90be818",
          "type": "default",
          "loc": [
            -1.07037353515625,
            1.3947802325597662
          ],
          "layer": "%5B%5BIMG_0117.png%5D%5D",
          "mutable": true,
          "command": false,
          "percent": null,
          "description": null,
          "minZoom": null,
          "maxZoom": null,
          "tooltip": "hover"
        },
        {
          "id": "ID_e96a085aaaf8",
          "type": "forest",
          "loc": [
            -1.06353759765625,
            1.398686307681761
          ],
          "layer": "%5B%5BIMG_0117.png%5D%5D",
          "mutable": true,
          "command": false,
          "percent": null,
          "description": null,
          "minZoom": null,
          "maxZoom": null,
          "tooltip": "hover"
        },
        {
          "id": "ID_c8d889bbbb09",
          "type": "forest",
          "loc": [
            -1.07818603515625,
            1.402592382803756
          ],
          "layer": "%5B%5BIMG_0117.png%5D%5D",
          "mutable": true,
          "command": false,
          "percent": null,
          "description": null,
          "minZoom": null,
          "maxZoom": null,
          "tooltip": "hover"
        },
        {
          "id": "ID_3a1ab8294bfa",
          "type": "forest",
          "loc": [
            -1.1134033203125,
            1.391108974879124
          ],
          "layer": "%5B%5BIMG_0117.png%5D%5D",
          "mutable": true,
          "command": false,
          "percent": null,
          "description": null,
          "minZoom": null,
          "maxZoom": null,
          "tooltip": "hover"
        }
      ],
      "overlays": [],
      "shapes": [],
      "files": [
        "Bullion Map.md"
      ]
    },
    {
      "id": "leaflet-map2",
      "locked": false,
      "lastAccessed": 1693866688532,
      "markers": [
        {
          "id": "ID_e96959a83b0b",
          "type": "default",
          "loc": [
            -0.92193603515625,
            1.415260458054461
          ],
          "link": "River-Lands of Ancestral Ith'Paraan",
          "layer": "%5B%5BIMG_0117.png%5D%5D",
          "mutable": true,
          "command": false,
          "percent": null,
          "description": null,
          "minZoom": null,
          "maxZoom": null,
          "tooltip": "always"
        },
        {
          "id": "ID_49e978b9882a",
          "type": "default",
          "loc": [
            -0.5430908203125,
            1.9164386548943453
          ],
          "link": "League of Joriele",
          "layer": "%5B%5BIMG_0117.png%5D%5D",
          "mutable": true,
          "command": false,
          "percent": null,
          "description": null,
          "minZoom": null,
          "maxZoom": null,
          "tooltip": "hover"
        },
        {
          "id": "ID_e8faaa597a5b",
          "type": "default",
          "loc": [
            -0.4884033203125,
            0.6098565265870528
          ],
          "link": "Protectorate of Winifreyad",
          "layer": "%5B%5BIMG_0117.png%5D%5D",
          "mutable": true,
          "command": false,
          "percent": null,
          "description": null,
          "minZoom": null,
          "maxZoom": null,
          "tooltip": "always"
        },
        {
          "id": "ID_899bfab80b9b",
          "type": "default",
          "loc": [
            -1.5411376953125,
            0.47711432754510463
          ],
          "link": "Emirate of Qaulhain",
          "layer": "%5B%5BIMG_0117.png%5D%5D",
          "mutable": true,
          "command": false,
          "percent": null,
          "description": null,
          "minZoom": null,
          "maxZoom": null,
          "tooltip": "always"
        },
        {
          "id": "ID_f83829ebd8e9",
          "type": "tower",
          "loc": [
            -1.434539794921875,
            1.9094137129136504
          ],
          "link": "Owohain",
          "layer": "%5B%5BIMG_0117.png%5D%5D",
          "mutable": true,
          "command": false,
          "percent": null,
          "description": null,
          "minZoom": null,
          "maxZoom": null,
          "tooltip": "always"
        },
        {
          "id": "ID_18fa1a98a8ca",
          "type": "default",
          "loc": [
            -0.417938232421875,
            1.374269091595805
          ],
          "link": "Raghain",
          "layer": "%5B%5BIMG_0117.png%5D%5D",
          "mutable": true,
          "command": false,
          "percent": null,
          "description": null,
          "minZoom": null,
          "maxZoom": null,
          "tooltip": "always"
        },
        {
          "id": "ID_fbebb89a3a1b",
          "type": "default",
          "loc": [
            -1.890869140625,
            1.4423828125
          ],
          "link": "Sirrhad",
          "layer": "%5B%5BIMG_0117.png%5D%5D",
          "mutable": true,
          "command": false,
          "percent": null,
          "description": null,
          "minZoom": null,
          "maxZoom": null,
          "tooltip": "always"
        },
        {
          "id": "ID_5b7959eb18f8",
          "type": "bridge",
          "loc": [
            -0.89727783203125,
            1.3701171875
          ],
          "link": "Eleyda",
          "layer": "%5B%5Bbullionmap.png%5D%5D",
          "mutable": true,
          "command": false,
          "percent": null,
          "description": null,
          "minZoom": null,
          "maxZoom": null,
          "tooltip": "always"
        },
        {
          "id": "ID_ea2abac918ca",
          "type": "lake",
          "loc": [
            -1.038482666015625,
            1.30810546875
          ],
          "link": "Arnecca",
          "layer": "%5B%5Bbullionmap.png%5D%5D",
          "mutable": true,
          "command": false,
          "percent": null,
          "description": null,
          "minZoom": null,
          "maxZoom": null,
          "tooltip": "hover"
        },
        {
          "id": "ID_c8ca884ba9a9",
          "type": "alps",
          "loc": [
            -0.921295166015625,
            0.94873046875
          ],
          "link": "Mezcoatl",
          "layer": "%5B%5Bbullionmap.png%5D%5D",
          "mutable": true,
          "command": false,
          "percent": null,
          "description": null,
          "minZoom": null,
          "maxZoom": null,
          "tooltip": "always"
        },
        {
          "id": "ID_ca8a6b0bd8da",
          "type": "pillar",
          "loc": [
            -0.557037353515625,
            0.76904296875
          ],
          "link": "Karyos",
          "layer": "%5B%5Bbullionmap.png%5D%5D",
          "mutable": true,
          "command": false,
          "percent": null,
          "description": null,
          "minZoom": null,
          "maxZoom": null,
          "tooltip": "always"
        },
        {
          "id": "ID_083b0bb8d80b",
          "type": "trail",
          "loc": [
            -1.430084228515625,
            1.37646484375
          ],
          "link": "Rio Insólito",
          "layer": "%5B%5Bbullionmap.png%5D%5D",
          "mutable": true,
          "command": false,
          "percent": null,
          "description": null,
          "minZoom": null,
          "maxZoom": null,
          "tooltip": "always"
        },
        {
          "id": "ID_fa08dbeb99e9",
          "type": "trail",
          "loc": [
            -1.337310791015625,
            1.55029296875
          ],
          "link": "Ollom's Creek",
          "layer": "%5B%5Bbullionmap.png%5D%5D",
          "mutable": true,
          "command": false,
          "percent": null,
          "description": null,
          "minZoom": null,
          "maxZoom": null,
          "tooltip": "always"
        },
        {
          "id": "ID_2a2869f94ada",
          "type": "dead forest",
          "loc": [
            -1.215240478515625,
            1.47314453125
          ],
          "link": "Tuck's old farm",
          "layer": "%5B%5Bbullionmap.png%5D%5D",
          "mutable": true,
          "command": false,
          "percent": null,
          "description": null,
          "minZoom": null,
          "maxZoom": null,
          "tooltip": "always"
        },
        {
          "id": "ID_39693a6a7a59",
          "type": "signpost",
          "loc": [
            -1.283599853515625,
            1.45166015625
          ],
          "link": "Lylesberg",
          "layer": "%5B%5Bbullionmap.png%5D%5D",
          "mutable": true,
          "command": false,
          "percent": null,
          "description": null,
          "minZoom": null,
          "maxZoom": null,
          "tooltip": "always"
        },
        {
          "id": "ID_59fb1aeb7b78",
          "type": "waterfall",
          "loc": [
            -1.279205322265625,
            1.22509765625
          ],
          "layer": "%5B%5Bbullionmap.png%5D%5D",
          "mutable": true,
          "command": false,
          "percent": null,
          "description": null,
          "minZoom": null,
          "maxZoom": null,
          "tooltip": "always"
        }
      ],
      "overlays": [],
      "shapes": [],
      "files": []
    }
  ],
  "defaultMarker": {
    "type": "default",
    "iconName": "map-marker",
    "color": "#1c1717",
    "transform": {
      "size": 6,
      "x": 0,
      "y": -2
    }
  },
  "markerIcons": [
    {
      "type": "forest",
      "iconName": "map-marker",
      "color": "#dddddd",
      "layer": true,
      "transform": {
        "size": 6,
        "x": 0,
        "y": -2
      },
      "isImage": true,
      "imageUrl": "data:image/png;base64,iVBORw0KGgoAAAANSUhEUgAAABgAAAAYCAYAAADgdz34AAAAAXNSR0IArs4c6QAAAeFJREFUSEu11UvoSFEQBvDfHyHPFcqGkpIoESJ5RBYeexuxsBMLhdjIhhCWdixslJ3XQrFRnkViYSHJzisRIs9G5+o6nXuuR6ZunXvOd+abmW/m3gH/2Qb+s381guHYhC84jo9/E0wXwWAcwdbk9BNOYyNi3VjgwiKIopUIRuMBJqBx0FyO/en4ljYupfWK3yUIh08wseNCOA5nl3EY2xLuaGv9y9U8gzF4jqEdBHcxB0txHsMSLvRZjcioSnAVCypiTsVDPMX4DPcslbWTIKJ+iVEVgil4hItYjkEJ+zVFv7KWwVqcqTiP+m/GMRzE9gx7CDtqBG3RSjzXsBCzcAtDMtBnzMft9n5b5Hm40ZHBi1TfEakJYghL9gHj8LY5bBNMwuOOi9Exa3APMypljKP7mFkiKNW1wV3BYqxCaLUeIzOidziJs7hQIoj2jDYtWXweFuEm9qQnn6Fogr3p+ekjB03DHeQ1vp4EjvKEiLnAjcMQenYq5Y+9nCDeT2BDK4336fvzJmkU016zwE3GqxJBc3ELlmBZGqy52IV9Pc6b493YXyNogNH7YaHPWKzLCHam9wPZ/im8/lOCUvDtAIrJ9f0y+xz0nVd/mRFRDFfYuY7a9533Evympt2wvhL9M8F3w7RYGeE1YY0AAAAASUVORK5CYII=",
      "tags": [],
      "minZoom": null,
      "maxZoom": null
    },
    {
      "type": "alps",
      "iconName": "map-marker",
      "color": "#dddddd",
      "layer": true,
      "transform": {
        "size": 6,
        "x": 0,
        "y": -2
      },
      "isImage": true,
      "imageUrl": "data:image/png;base64,iVBORw0KGgoAAAANSUhEUgAAABgAAAAYCAYAAADgdz34AAAAAXNSR0IArs4c6QAAAdlJREFUSEvF1UuoTXEUx/HP9RgojxImUoqQRGRg5hmSPPIYUQYKSZGJgfIohlKUgYGBiaTckolCHklEwoAUeZZ3pDxDS2vfjt2+x3Gck3+dzm7/11rftdZv/fe/Q5tXR5vjqwfojc14isPNJlIPsB77M/B43GoGUg9wDSPRDyewsJWACHwHOzEW8/EEo7ELWxuFdVdBZBxBR2EozuIrXmFw/j5iH3phLb5UQbsDvMGlhPTENlzFW5zHcqzEggy6A9sbBazGQXRiBDbhNIYk4DW/pq8v9mAmBmI4vpch5Qoi2xfpUNhG8Ll4iDP5ckW2bTaW4EgmsvdPgOj3I/QoGa7DgdK7k9iAaYjAH1Kv38zKFYTTvEYnBC9T8MJlGY7V+tcCosfP/yJ4lek7DMK3YrMWsAqHcuMTbuIB3qegE/JM1MvhB6bjXBkQPd+Ci7iPZ1UTgf4YgxlYk5NTBkbbhuFzbJQ1GIA5mJzOMX590jjEv4zQ6XH6TswJW4p4LtbUPC9dgCDGJCyugFa15AqO4hRuI1oT52AWpuREbaytYBGONynw3TyYFxDPIXTXKlr0L4ByXvdwA7vjvx2AAhjt7iwA43AdcYu1YsWXd1Lo81/v5FZUUvfSbwngJxm8Wxm//iJmAAAAAElFTkSuQmCC",
      "tags": [],
      "minZoom": null,
      "maxZoom": null
    },
    {
      "type": "arch",
      "iconName": "map-marker",
      "color": "#dddddd",
      "layer": true,
      "transform": {
        "size": 6,
        "x": 0,
        "y": -2
      },
      "isImage": true,
      "imageUrl": "data:image/png;base64,iVBORw0KGgoAAAANSUhEUgAAABgAAAAYCAYAAADgdz34AAAAAXNSR0IArs4c6QAAAa9JREFUSEvV1c2LT3EUx/HXKBJKbMhiFphYsNAkSrbGwoKSh7Kz8RCxUqyUhb/Aw8aIhZA8pKiZNU02hIWUh42aKbEgKYNOfX/T7dv3/u69iynO5lfn+7nnfc/nnPv9DZjlGJjl+v4pwBzMxyCOYxMO4A1+1znRpoONOIEdCTCvUiwKv8V2fChBmgBncK7FnO5gd1fAWjzDogbAWTzCRFfATexp8fbr8LrrDNZjDMuyB39gKg26au80hvEiB5VmMJTaXVIRR4FrOIbvWIn9OI0FSXcIl5sAc/EFCyvC9ziJ+wUbnmJzyl/FEUSXM5F3EHsegPjtxRNsqfG4CgjJN6zBp56+CTCOffjcEhCysHNxsrJ4VcSX+jEVjDePDuriFM4XDlfhXeSrHYQtN7AasXoRB3GlDyBmFbbkEet9OweM4HGm/JnNo8T6U0jGsC/mgAs4XBD3u05iPtF1L7al72cmUX04iLHLeSzHZCG/FC+xonI2igd4iF95B3WAV9iKrxnkerquS7ZtwPO2gNDdwt6s0l3srFmAsPtoF8A97OoAuNSbZ9P/QZ8NbXf0/wP+Art/TBlsWz2CAAAAAElFTkSuQmCC",
      "tags": [],
      "minZoom": null,
      "maxZoom": null
    },
    {
      "type": "bridge",
      "iconName": "map-marker",
      "color": "#dddddd",
      "layer": true,
      "transform": {
        "size": 6,
        "x": 0,
        "y": -2
      },
      "isImage": true,
      "imageUrl": "data:image/png;base64,iVBORw0KGgoAAAANSUhEUgAAABgAAAAYCAYAAADgdz34AAAAAXNSR0IArs4c6QAAAY1JREFUSEvV1M1LVlEQBvCfaYlLEQOjZWDgxkXQfxDYpnSXqzbV1o/aBEGBbg3caVCtXPqxSKH/oKCNIEiIWxeSuhP6MgbuldPpva+X196g2cycM/c8z3nmzNwObbaONuP75wSLeHBOVa/wsMTIFSykyRaJ4pKPqgjK/ROMYhURh491xGFxsRXcLeLwsf6j5PnGfdwpDn7AXhGHj3UAhQXhTQwUcfhYx/4a3lYp+I7OFktTHvuZYuQKyhKUH+9gGe+xhS9Fog9DuIUxXMsudYpbRRBKZjGDiJtZF57iGSIu3+j3oEiUCm5jI0PtxyS6sYvXOE6+GcF6XYJc2Q18TLrkBZ43kJV2WVMFKcF1bOJiAnil6LCc40yCRrVewr0scQnf6nRbnX/RAXozsAvJ0DXlqUPwNStPAF7G/t9SsI3BDOwlHiOG6twK5or2zIGmMI8fzRjqlGgYnxB1zy1mYRpHVSR1COJslGSiAiSGbRzvGnVWXYIefMbVCpLo/0M8wZu0w+oSnPWWlfn/n+AXbmJHGWA9FjoAAAAASUVORK5CYII=",
      "tags": [],
      "minZoom": null,
      "maxZoom": null
    },
    {
      "type": "woods camp",
      "iconName": "map-marker",
      "color": "#dddddd",
      "layer": true,
      "transform": {
        "size": 6,
        "x": 0,
        "y": -2
      },
      "isImage": true,
      "imageUrl": "data:image/png;base64,iVBORw0KGgoAAAANSUhEUgAAABgAAAAYCAYAAADgdz34AAAAAXNSR0IArs4c6QAAActJREFUSEvF1UuozVEUx/HP9UhKonAHiCilPCK3zMRASSR5JhkYiRFjE1G3iEzMKMkjMVCSicLMQHnEzGMiz5CJkEdL61/n/rt3/89xOtmz/3+vtb9r/dZea/fp8err8flKgLFYinvdBFEC7MZWrG4DEMGcw0oswtvKpwR4gvnpdKcBsgY30uYd+psAx7CfvxI+zah+FiAh5f3cv4TtTYB5GEx5luE5vhcAEcgSTMMt/GgCTMALTMEBHG+jDsOajFSD0DN0jfURA5lFx5w6IL734WSeFN+/8RjL8bVTQh0wBkdwBaexEBsxE3fxoFtA5b8Aj/IWXcCOTg9uKvIzzEmjX1iFpl5oq8ghWcgTsrSuNwnsugZxJY/mPX6PyXmLZqRki5N6FhNrQXzBrnoa9SKvx2s8xCFswVzMzm6+lv8PjlCTwxiyV5pFJ7AZEX21xuETxtcArzA9r3Fk/a2pyLF/Cpuy/Sv7Pfm/nkBM3JsYhb2tNqUMzmSxJ+VpofnnvLqtgA+YittYkY0ZPlGT4oNzPgGVHNtwcRjtI/IYKyHn5dyPaRpTtQi4ig0YnU5rcb0GiB7ZiWjGWXiZ++sq2//6Jv/rdBji1/MM/gC5w04Z+1KKwgAAAABJRU5ErkJggg==",
      "tags": [],
      "minZoom": null,
      "maxZoom": null
    },
    {
      "type": "base camp",
      "iconName": "map-marker",
      "color": "#dddddd",
      "layer": true,
      "transform": {
        "size": 6,
        "x": 0,
        "y": -2
      },
      "isImage": true,
      "imageUrl": "data:image/png;base64,iVBORw0KGgoAAAANSUhEUgAAABgAAAAYCAYAAADgdz34AAAAAXNSR0IArs4c6QAAAc1JREFUSEu11UvITmEQwPHfJ7ci7FBkQ7KQpeSSJBvZKCKhLCgrkkRWiqgvJQuXDQsp1sjGJWFBykbkUjZYkFtI5NJo6PR23nPOo76zOufM5T8zz8w8A4b4GRhi/0oAC/ETt0qCKgGE47mYilddIV0Bo/EZw/AGk/CjC6QrYD5uVhzOwiPMwJMmUBdARH0DAfn7XMUzbMQC3O0H6QLYguMNUV7Aiv8FRCnuYGwD4Fueybs6nbYMrmBJh8NcjzOlgDm4X2P0Hb8wsiI7gm2lgIPY1WMUju9hAqZXZOewphRwHqsqRjFc+/EAW3tkZ7GuFHACmytGp7Apv3fjQEUWwGOlgHm4XTHaicH83o7D+f4W0/CpFBD6kfraNHyKxbnwrmFm/u8bfcjb2jR2UHRIlGZ4T4QfsRdHm9q4H2BZLrfneIEp2IDZmUGshtN4j3GYnMMWa+V6tvEfbj/AV4xKxUM4idf4kjZj0mkc9MpKBgGciJjuvoARCAersS8N2ob5MfbgMiK4f6u8N4Nw/jIHqVrzmN7oqIu5OZdiOWLaqz5C72H+r80glHdkiuEwLpcPiAOtu2BiXcQZjM+SLcr1cqmpRG3lKJK3tWmRszrl31xDWBnqa+fzAAAAAElFTkSuQmCC",
      "tags": [],
      "minZoom": null,
      "maxZoom": null
    },
    {
      "type": "canyon",
      "iconName": "map-marker",
      "color": "#dddddd",
      "layer": true,
      "transform": {
        "size": 6,
        "x": 0,
        "y": -2
      },
      "isImage": true,
      "imageUrl": "data:image/png;base64,iVBORw0KGgoAAAANSUhEUgAAABgAAAAYCAYAAADgdz34AAAAAXNSR0IArs4c6QAAAcNJREFUSEvF1c2LT3EUBvDPeCs1s1BiQTSlCaFYsJEoL6NR2LGzsPEPKIVSFspG2ahZCAtKISZFTaxkM0pJ+Q+wYCGEvHSmc+v+rnt/vmGas7p97znneZ5znvu9A2Y4Bma4v1kBmItx7MZ6vC9QOR/XsAMb8KaqaVNwD/vwGmsLAfbifjZ9i6VtAEswheW4jKP4UcA+UjZlbTzfwOE2gNM4hQN4hE9M72gnVuNiH7DI24ggOYlvbQDrcu4XkvkRnMUy3MHBQjU9af1cdDvVRMF/B9iDM9iSdCqAUBnxolRNl4JYbv1dBfA1Gy/4V4Cf6aTreFgbUZxHNImN4DGG8aUO3qUgGsVSg3k8Vwq6APZnznGc/xuAu7nw6rsIYouxCk/zXZjiVVo6rP4An9sUxFk0qiv4kI121UYU44tGC2sAH7EoGufZRBMg7qEn2JwuutnhmDm4lU3CWYdwMonFzkYrgk2AIbzDvD+4ZAW242qfvOkJNAHGMFFgwUs4hud5e7aV/AYwiLhJg1lJhCW34UpHcg9AzDHYxGxL4xxO4CXWtBT1AMSP5VnB7Ot9vmMltuYV3cRo3UEp++K8WfknF7MrSfwFsIxcGVqQPacAAAAASUVORK5CYII=",
      "tags": [],
      "minZoom": null,
      "maxZoom": null
    },
    {
      "type": "cave",
      "iconName": "map-marker",
      "color": "#dddddd",
      "layer": true,
      "transform": {
        "size": 6,
        "x": 0,
        "y": -2
      },
      "isImage": true,
      "imageUrl": "data:image/png;base64,iVBORw0KGgoAAAANSUhEUgAAABgAAAAYCAYAAADgdz34AAAAAXNSR0IArs4c6QAAAXpJREFUSEvV1E9LVWEQx/GPiog7/xCBhm2iXOQbCCMRlFYpKK6FXkCEi8A30LIWrhXXCi5DUQTFNyC0KDduCgvFheAiiGIuR70ennPP9aqgz+pwZub3fWbmmWlyy6fplvXdOcAb9GGu3syvkkEHjqhk/Qg/64FcBTCMjUz0PT7fNGAHLzLR3+jB3zJIWQaTGMMH/MiJ9ePbdQC92EUX1jCaE5vC0nUAKxivIbCIaTzPLrGV8i0qUdw6XklbDcAvROMjyxa8xXzevwgQqUf9y842XlY1/mG9gEN0l6njXzYXZ66vsVodl8ognL7UIZ5y+Zr15NyWAkRNBxoEnKITf87i84Bo6jHaGwTE4AXgpAjwAAdoLgB8z/4/rXGBQcTUV04+g3jXC4ngaOYnzGS2+H6XiA/zR8wWAZYxkQDEEL3K/a/eTdWmdYwUAfbxOAG4lHZmH8Jmwjd2VqzzZImi+625oKj7s4Ka7+FJzhYa5xugbJs2+Jguwu4/4D835jcZBMJuVQAAAABJRU5ErkJggg==",
      "tags": [],
      "minZoom": null,
      "maxZoom": null
    },
    {
      "type": "dead forest",
      "iconName": "map-marker",
      "color": "#dddddd",
      "layer": true,
      "transform": {
        "size": 6,
        "x": 0,
        "y": -2
      },
      "isImage": true,
      "imageUrl": "data:image/png;base64,iVBORw0KGgoAAAANSUhEUgAAABgAAAAYCAYAAADgdz34AAAAAXNSR0IArs4c6QAAAXlJREFUSEvN1T9LVmEYx/GPCCaIGrgoqQkWiG/AV9CSRI7V1KCoQ/QaGsLBrSkVV6OxJQdfQDTpIg1KqJCIi+KfyhbjgvuAPZ7jc54nH/SGw4Fzrvv6Xv/4XU0afJoa7N+NA1rwEBN4hPsp422sYB6b+FNUiasyGMUS2inM9BzHeI7PeZAiQC82cIRJfMUhzpKTO7iLEcyhAw/woxJSBBjHAp7hY5VBCJsPiDuLZQER9XucJMAnrGI/OYiad2IWL9CGqZTNP4yiDDJAUfBdeJucZjbTKaghxBD8ih/1AsbwEvHOzhesJegbxHMJ8DQ1rwczV9T+O9bxJMfmAMPYywN8Q6RY5uygv8IwRrYbP7PvlSVqRsx/TE5rGcoFm4i8D6cX7xX14BXe1Qh4nXen3ibnsa91TG8/IJOKWtpQk1TcSzJcdpJ+YxC7ZbUo7B4nESsj1yF4y3npVttosXBChrOFM5CcbKWFE4pb98Kppf6FttUy+G9IwwF/AV66SBmARr4aAAAAAElFTkSuQmCC",
      "tags": [],
      "minZoom": null,
      "maxZoom": null
    },
    {
      "type": "geyser",
      "iconName": "map-marker",
      "color": "#dddddd",
      "layer": true,
      "transform": {
        "size": 6,
        "x": 0,
        "y": -2
      },
      "isImage": true,
      "imageUrl": "data:image/png;base64,iVBORw0KGgoAAAANSUhEUgAAABgAAAAYCAYAAADgdz34AAAAAXNSR0IArs4c6QAAAdlJREFUSEu91UuIT2EYx/HPaMglEkJTVsjGXrKhScmlZNyKyEbZKSW3EqlRFqQQFhYaYSPXZBqxkSwkC8pSkqywUO566vlr6H/OvEfGu3nr/N/z+573eX6/599hmFdHof5ozMM4PMWrwveUAEK0H/MHiZ7B1Xz+pQ5WBYjna3AEEzEGG3EPTzAJo3AcO/G5ClIFOIfN/LrhBWxIkU6MxHn04Bnm4kc7SBXgPe4k5Bu+IvZYS/EAH7Aal7AHvU0AIbYJfdnYo9iLVTiBw9iXpfuYkPVNAG/xGisxPp1zAAsxM/eXOIhd2IqzTQBR/5MYiwF0427uobMIt7PR4bAl+N4EEGdn5xe2rv4Cc1LkItZhG8KybcXjbEkOFuMQujAjAc/TqtOGClwJIDROYS0mp2D05zGW/ytAhGl/Oio0w8anM2S1jLobTMEsPMSWrHUELNYnbM+bjcAKXGsXtjpAuCiCNDX3ywixWJGTGB3XM5Axp8LSMZ9+W3WAGHJR8/D7AtzMuRQC77Asbxa324FjTW06VP/i90h0zKDdVYdLXTQh09sqUfj+fjb7r5vcysl0XMk/nMFij7Lub6om6Z9Bi5reKKlLwZnQuvXfAQUf1vxIaZObK+cbww74CcbmWBlQFmY8AAAAAElFTkSuQmCC",
      "tags": [],
      "minZoom": null,
      "maxZoom": null
    },
    {
      "type": "hot spring",
      "iconName": "map-marker",
      "color": "#dddddd",
      "layer": true,
      "transform": {
        "size": 6,
        "x": 0,
        "y": -2
      },
      "isImage": true,
      "imageUrl": "data:image/png;base64,iVBORw0KGgoAAAANSUhEUgAAABgAAAAYCAYAAADgdz34AAAAAXNSR0IArs4c6QAAAktJREFUSEvV1VnIz3kUBvDPi7Fml4hoSpbIGikXtuEGzaQsxQVKIqGQXclWSmRS1CRXLohGuGCkiQvKfqEsjWwzWUqWLA2Gjs6r1zvvz/8vXPjWv/7L9/c85zznOc+/wjc+FWXid0MDnCvz/odr5RDEnb/wL7rmk00xGxvx8lOk5RC0xj0cxJgEG4Hf0RvXvpSgFy5gOdZWAfsBr0pJVk4HfXEWS7E+ASfgAJ7jAfZhRk1kRQStsAbz8R/u4xa6J0jMYwG2YCDu5Ot/HEUE8dB+9E/gOdiMidiNm3iIPl9DosBojBsJFkP/A0PRDI+/ZMid8DrBd2I8mmMZVqRklxFzuoKn1cmKJKqD1ViEPzEMRzAoCWKgof+A3I/z2ckQXKxKUkSwF2NxEj+nW6K6u2iH3zANXXAVo7EHYd0O+KeSpIjgWVpvCt7gp9R9EnbhOhqiLd4mWHvczjjpV4ogdJ+LrXmxDcJJoX2cWLDYiw1V5KiXsRHualmKILIn3BIdhFzVzyicwJP8oRG2YTKmIgzx/hRJ1BmH0RHbMRO1qtgyqo2ueiJy6ZeUK4Cnp6yFBKHri9zgxfg7pZqHTTV0E3Kewq+5hBGAlypzqnoH8TmSszbG4XjuQeD+iCVokQWEo+L/4WjmURPMwro0xbEiicLbhxB5FJWswmk8QrgrKg65oph4XxcLsTJtGqSD827hDOLhHYjUrF8wq3BSbHrEyJlctBhydPThlIrrymEG0Uj0SIkipsNpw7OzKCISNpL3o1OKoIaZft5X3z/BO/mTgBlqfmnlAAAAAElFTkSuQmCC",
      "tags": [],
      "minZoom": null,
      "maxZoom": null
    },
    {
      "type": "lake",
      "iconName": "map-marker",
      "color": "#dddddd",
      "layer": true,
      "transform": {
        "size": 6,
        "x": 0,
        "y": -2
      },
      "isImage": true,
      "imageUrl": "data:image/png;base64,iVBORw0KGgoAAAANSUhEUgAAABgAAAAYCAYAAADgdz34AAAAAXNSR0IArs4c6QAAAjRJREFUSEvN1UmojmEUB/DfNc+ZU7IwbyQiQ5RElLBRsmLDisKKWMqCJGVIyMJChFIkwwKRIsqQBSVTSjJkyHRNHZ1Xb999713gq3s2X+/zfOf8z/+c/zlPgzpbQ53ja7UAw3EW4/GqpSq0xGAoHjTjfAujsRrb/gZgDTZgFi6gM+bgGAL4HtriPkYmQD8swO4yYBWD7niOLniSAdZhPeZjS57twzLMziQuYyyG4XEBUgUQgV+gKx5iJu6iE97n+UZsxVOcwkEcz6CPkuWP+K4FaIOLmFqiGSCDsBMr8RMDMonDWbroxd70uYLp+FoFEHUNqpNqGncJq3ADH9AXX7JHZyqavAgB3oRBx8ysR43TeQzEiDzfhdu4k40PRmUblWVtAjABV//DdB/FwihnuQftcTJp/yvGMwyJPhQA8RuTGYoJCwVsx4GUbNT9E77lfbucjW7Z8CVYgRBJ2JFk8KdE43A9L0MNa/G6BRr7c9CWZ9Pjr72xCUvTL2biZsFgLk6ktHrhYyn4oWxwBIvGhr3NbGNdhIwLixl6gw6YFyUvACYj9BsaD03vwPf0qgIokwuQEMdgzMDEvJwSMQuAQAz1jMnLa9gcFHNafw9NjUW9Y1eFMGJ+ynY610pjWUU9E6TQeuHQmMstFluUJqxPDmP//P6c8xOrOxKLIYtqVD44i3PPBGBtZlV9f4dpybbJfXPvQQSOhkUdQwBFjYsJf5lrYw/O5dqoAm+9T2ZltlWHdX/0fwGzlXQZS24FgwAAAABJRU5ErkJggg==",
      "tags": [],
      "minZoom": null,
      "maxZoom": null
    },
    {
      "type": "mountain",
      "iconName": "map-marker",
      "color": "#dddddd",
      "layer": true,
      "transform": {
        "size": 6,
        "x": 0,
        "y": -2
      },
      "isImage": true,
      "imageUrl": "data:image/png;base64,iVBORw0KGgoAAAANSUhEUgAAABgAAAAYCAYAAADgdz34AAAAAXNSR0IArs4c6QAAAZ1JREFUSEu11MGLT2EUxvHPmAZNWSgkMpGQbAjRmNU0lMTekrISKysWVrKxUIqaFTb+AKamKYspjTINC0VEaRpllEyzUFLo6Nzpdptf9/5y5928m3Of73mec97bY4VPzwrr6xZwGn/wpGlj3QA2YT6FN+BbE0g3gBu4mqLncL9NwAA+YhYbU3gzftRBmjq4iSvYg2N4iJhH7SyaALbjHV7haHb8Nd0cxm7cxnW8qDpqAriFyziE1ylwBxdxAdcQTUR8cceWLZ1OgBOYRn9m/wwjKTqcwp+xFot4gEu4lzVLkOUAe/EGX9LyGYzlDN5maxFZzCOETmEcT3M+68vDXw7wHEfwC6vrtgRDKbwfZ3EQL4vvqoCw/B2TWTyDHTWQqWyoN+seI1z/O1XAcUxgELEpEUlfAxflkt9YV8RUBqzCe+zEQjqp674Texc+VB1sxVyX3XYqjxW+WwXETo+2BIho98WWFRFFzp+wpSVAyGyLRArAgfJqtQQ5Ge+jAMTrjMfU5jmPRwUg7jVtquNneQYta9f/7FoDNvld/xfsL6akShmpHoxOAAAAAElFTkSuQmCC",
      "tags": [],
      "minZoom": null,
      "maxZoom": null
    },
    {
      "type": "park",
      "iconName": "map-marker",
      "color": "#dddddd",
      "layer": true,
      "transform": {
        "size": 6,
        "x": 0,
        "y": -2
      },
      "isImage": true,
      "imageUrl": "data:image/png;base64,iVBORw0KGgoAAAANSUhEUgAAABgAAAAYCAYAAADgdz34AAAAAXNSR0IArs4c6QAAAdtJREFUSEvN1UuoT2EUBfDf9YwJYuA9YWrATDKhMKJkIgMDKUkMlJIJE0Oi5DEyESWvgaQkRQaiDDySKImivCXl2da++vruPf9zpFt3j85jfXudvfba+/QZ4ugb4vyGBcERXMeJlmon4AZ+YTE+BL6tgvF4j/uY30KwFzsTE9e7uhCsx3H8wDw87EGyGmfyfVyfayKYg2MJXonleegyVvQgGJXSBCQk/d5EcABbB0n0EZPw81+cV/cg7l9gWkOSHViDDbjXhagmGIt3GNdw+Fsa4yi2VJgpWIQL5fOaYCLeYETL14W+YcsviRuJi1iS1UeOP1ETRPmnu5SeX3szsUtxJa/vYkHOwwCCSy1OKbn3YXvhsGXFy9l4XlcwJkuOcrvEJ0xG9GUWHiNybEqbD5AonHMKZ5M97tdhYQ+2kOZqDmMMZUT0ZwZe1xVEP2KP1BHDFXKEAU7iGt5iZuJv4UlljHDYoZpgdGq6EaHhswQdxteCdXo65RE+F8/3YBumlvjSRatwfpAKYv/sz320FiFLnHuJWCV3ijPRv5j0v0qUBFHS5i7drTC3EdZ8mrPwoH8P1RKFFOGA/41XmNsvX1nBQYT+TRHYWCVdYjeiJ60/nC7JemLa/mjDn+A3j/BaGfZ3gRgAAAAASUVORK5CYII=",
      "tags": [],
      "minZoom": null,
      "maxZoom": null
    },
    {
      "type": "phantasm",
      "iconName": "map-marker",
      "color": "#dddddd",
      "layer": true,
      "transform": {
        "size": 6,
        "x": 0,
        "y": -2
      },
      "isImage": true,
      "imageUrl": "data:image/png;base64,iVBORw0KGgoAAAANSUhEUgAAABgAAAAYCAYAAADgdz34AAAAAXNSR0IArs4c6QAAAepJREFUSEu11cvLTXEUxvHPS5Lcc4+SMHNXIhMSRcnIQJFEiFKGykz+AANiwIRSZIAoIkZSShmIcktCbkVCyKWldd5Ox74db/bknNrr93zXb61nrd3jPz89XerPzvg7Tc91A1iEGym8uO1/JasO0A9XsSRVvuTvICzHLjzC7jJKHWArjuThl5iOX3iGkYjz3zEB74ogVYDI/gk+Y1YKtTTGYwuiF+dwDJu7BezDXmzAiYpCX8J8jMOPzrjWDWbiAC7gPF7gMYbgOp7iNG6mwEKsxSR8xDrsx3Gsxsrsz90WYEZedUpBpu8xFP073kW2IT6i4EyUNkC9gIiJmi/FKkzG23TQWYzNLOel2G2cxGuswTKMzptexDX8jNiiJg/ENwzAcEzMTN/gUwIGY0ze7Dk+pAni7Nd02p/QTkBkGvXvLEfTwQ0Lh5VjNgoBDzCtqVpJ3MOEFAJ24GAfAdvbhvOvEkVpbmHuP0JiraxoNbisycNyBkZ1CYlZifrH6uh9ylZFePhMOqkJJ1wUw3e/bJKLRA5jWwP1GLiIO1oUW7Xs4l0M1JwayCHsLIupW9dTca+iVGGIBVUJ1AHi7KZcxy2dU7iCPYiv3Ku+AsK6Ud+NuX/Wt9uwrkdNbhAasU0j28t1gt24qFutwvjfortbGQ65zXcAAAAASUVORK5CYII=",
      "tags": [],
      "minZoom": null,
      "maxZoom": null
    },
    {
      "type": "pillar",
      "iconName": "map-marker",
      "color": "#dddddd",
      "layer": true,
      "transform": {
        "size": 6,
        "x": 0,
        "y": -2
      },
      "isImage": true,
      "imageUrl": "data:image/png;base64,iVBORw0KGgoAAAANSUhEUgAAABgAAAAYCAYAAADgdz34AAAAAXNSR0IArs4c6QAAASlJREFUSEu11b8rRlEYwPHPK4VSIjJiMUj8BQZKMVkZ5Q9gZWFiZZdsrCZKMfgL5EeZMIoolJTQrTud973Ofd97nfE5T9/v6ZzneU7FP6/KP/PVI2jHfHqgXbzlOVxewSDO0ZpCPzGKm5gkr2AB2wEsie2UJVjGegBbwUZZgk0sBrAtLJUl2MNsANvHXFmCE4wHsFNMlCW4wlAAS2LDZQke0R3AntBThqAJX1Q15Q+a8f2XJE8fdOI5A9KFl6KCPtxlQPpxX1Qwko6JWpxk76KoIBlyWdVyifcigl4MRCrlFg9ZObFHPsRURHCE6UYFSXONRQRnuG5E0FKj9rM4SU8kf0TVyrqiSRzUKZjBcWjIEnRgFW2xUZDuf2ANr3kFObnxtFgVxQmRjF/CDSwZ26YO0wAAAABJRU5ErkJggg==",
      "tags": [],
      "minZoom": null,
      "maxZoom": null
    },
    {
      "type": "ruins",
      "iconName": "map-marker",
      "color": "#dddddd",
      "layer": true,
      "transform": {
        "size": 6,
        "x": 0,
        "y": -2
      },
      "isImage": true,
      "imageUrl": "data:image/png;base64,iVBORw0KGgoAAAANSUhEUgAAABgAAAAYCAYAAADgdz34AAAAAXNSR0IArs4c6QAAAihJREFUSEvF1VmojWEUxvHfMZZ5Ji5cUTIrSaSklHJBxuLGGKFMRXJBkqkMFzJHKcUFMifigogSMoUkSZlDiYwtrVPb6Zzt1HZ47/b+3nf93+dZz/q+MjW8ymq4vv8KOIiRf1DYH5eL7Smm4BBG/G1A6yy6A4WA3ViDpjiBlgkOBY8KlH7Pc6/KL1aooDeuoA5qYS8m4BjGY13acRyP0QhxpiEuYBvOYg8G4HpACgEbMDfJ7fEeXfEM3XASH9E8/4/b3sRCrMVF7MdGbML8ioAtmJGA21iOp/iAN9iFO1iMPql0YO6rn+d+4CHWY2sxQGFvvyU4vA9b4uDg3BCKogd3cQpH8RJ18aW6gHJY3C5siwLRq304ja9ohjYIRRNT6axigMOYk36Hr11wAOMyAGFJO0zCZHTAc7TN26zE0qoAOzE9kxCHwv+49T30wBO0wNuEjEHENYqeRygdhHeVAaahFUZhO25heMbyPrpn4YhjWBFKXld3kiNFU9OWBVhWkIyIczyfhxdokgPVEVPQGUewKhUswaeqLAqfIxGR68h/rJiB0TkHtdELfTNNMWydcsiG5P7Z2FwVIOLVDzfQM5MTURyWUxr2nMPVtDBiHMAoHhMc4FAzs1iKolHx/jmDBhiLoZV4HY2M+YiC0a8H+Jw2Rwh+e1UswuoSP0ChJoZtBa5VBDTOAYkUlbJCfdh1qSIgfsdbtF4p1TNFYdOv9V8/mSUK+UcKfgJXrosZv81l9AAAAABJRU5ErkJggg==",
      "tags": [],
      "minZoom": null,
      "maxZoom": null
    },
    {
      "type": "ruin",
      "iconName": "map-marker",
      "color": "#dddddd",
      "layer": true,
      "transform": {
        "size": 6,
        "x": 0,
        "y": -2
      },
      "isImage": true,
      "imageUrl": "data:image/png;base64,iVBORw0KGgoAAAANSUhEUgAAABgAAAAYCAYAAADgdz34AAAAAXNSR0IArs4c6QAAAblJREFUSEu11TusT0EQx/HP9SpciQiJULkFhYhHvAuFElEQDZ2CjiAhoVJJKBA6GhWNUHiVCom3CIWCgopIiEhQeGdu9i8nJ7t/e/zdqc45M/v77uzM7BkyxjY0xvq6ACZgO37hHL7XbK4WEHH7cTSJHkzPAetrtYB1uMafjEN4A278D8A8PMbkhthtLMYSPO8HqclgEy7hMuK5aZvT9yKjBrALp/AOM1pKu3F60AxOYA9eYG0Su4m5OIm9gwKupoLuQ8DCQvQ4wrdxUMAWTMctPEti87EG73HxXwATMf5vLdjy/8C39ppckYfxClM6Aj5hDj431+UA57E1Bd3Fqg6gC9jWDxDHEuc6NQU9wtIOgI+pXnFco9bOIKb1Q5rcuNxqxI/gUNL7imn4UgIsxJPMjmPBYZxNvh3pvXl99JYtwtMS4AxicduaM9Dz9Wah9x6DGMMXm9iZA8T5x04nJWfcPdHrPzGzUIe3GJdmZEECxDFFZqN1aNZgFl5nhO5jZQFwDysyvtl40wYsw4NMcLTq6gLgTqGNl+NhG7C+cK+8xLEC4ABGMr4ruJ5r0w4tXxda8z+oUypE/QZJsEwZnOrjIAAAAABJRU5ErkJggg==",
      "tags": [],
      "minZoom": null,
      "maxZoom": null
    },
    {
      "type": "archaeology",
      "iconName": "map-marker",
      "color": "#dddddd",
      "layer": true,
      "transform": {
        "size": 6,
        "x": 0,
        "y": -2
      },
      "isImage": true,
      "imageUrl": "data:image/png;base64,iVBORw0KGgoAAAANSUhEUgAAABgAAAAYCAYAAADgdz34AAAAAXNSR0IArs4c6QAAAYVJREFUSEu11D9I1lEUxvGPSBAoNiSEtokUDSEIUaNr9EdwcbIpEopoERraXQzaooJqSZpcNBFaG0QaGoz+QUhLkNiQoC6VcuAXvL2+v3svr3jXc87zvec5594Oh3w6DllfCeAmztZcZBUPU5csAXxHX41IxE4eFNCDXzUix7B5UEDUf8apJqEvOJ2bYc6i27iDAfbN6w8C8gz360ApwGPcyN2wir/GRfxtzk8BHmGooSByzyeAsU23SgFd2GpKDpu+JgDrOFEKeIP31Ybcrfx/ifEE4DeOlALCy7DkKa7jDD5k5hE1naWAHRzFVSxUhRN4noCEpd2lgH+vdxvf8ACzLebSqLdWrfN/jLotmsNYQ+ZbjCLAdecepks7iP/lU0PLPzCCjzXq0eUgYtBFHUTSDKaq7F1M4kkLQMSu4UUreOqhRWwF56rCsKe/hcgiLtf5lvuLLmA5s57DeNcu4Dg2MoBe/GwX8AqXMoDIudIuIB5a/JKps4T5dgEZ7Xw4N+S8QiZjDzvAQBlw6froAAAAAElFTkSuQmCC",
      "tags": [],
      "minZoom": null,
      "maxZoom": null
    },
    {
      "type": "port",
      "iconName": "map-marker",
      "color": "#dddddd",
      "layer": true,
      "transform": {
        "size": 6,
        "x": 0,
        "y": -2
      },
      "isImage": true,
      "imageUrl": "data:image/png;base64,iVBORw0KGgoAAAANSUhEUgAAABgAAAAYCAYAAADgdz34AAAAAXNSR0IArs4c6QAAAidJREFUSEu11UnIT2EUx/HPa8xUdkoyy8ZQWBizQKaShZXYkgxl41VWlKE3C5QyLEj2FiLJUCQSIt4NMqeslPk1d/Rc3W73f+/778+pf/27zznn+zzn/J7ztPnP1tZE/iGYkfx/4TLe1cU3A9iNrTnAEpxrBdADfSoSxCm+4WcVpOoE+7GmBvAJB7EDP8p8qwCR/DCuorMkeBmGpu8fcAybin5VgP54i+NYWwKYgHs4hTjJalzH3FS6PyF1TY6dv8aCBqV6iCdYjFU4gWuYjy/dAdzEV8xuACiub8ABbMHe7gCe4RZWNADEepRxe1rvhZNJfSPxoqpEC5POY5d3SgADU1nK2CHhRTgfgOmpOeEYuj6Kzeho0Nx8wtj9GHxGb/Qs0LqKgGz9NJbXXLTwDe3HplbiSAHQFTIOQNzYduwq0PcgalxnIc+ZJYqMnB1ZD0Z0M1kdLL8+HC/zTb6COc1kqPA9hHVFmc7DhX8ECIk+LwIGJzWNz9XzFR4gJDkV/dIGQjW3ETMoRsaw9D3keSnd/PhfOipGp1LdL+i/L+INCDuLUElmUzAxDcYYHX8t68EkXMRGnEnSC03HrmMc38A2vE+Rg7Az3aH16TQh2bgLS7EPUfLODBD0u0my3xG/AERAZnHkmEth8RDlBRJ3IQAxKuIXj9DkKG/eKcbzqDQJx+JNavojDMA0zEqAmJgxoz5iXIqJN/txinmaRnjtuG5ZVHXvQcuA35PqdiRaU3lwAAAAAElFTkSuQmCC",
      "tags": [],
      "minZoom": null,
      "maxZoom": null
    },
    {
      "type": "signpost",
      "iconName": "map-marker",
      "color": "#dddddd",
      "layer": true,
      "transform": {
        "size": 6,
        "x": 0,
        "y": -2
      },
      "isImage": true,
      "imageUrl": "data:image/png;base64,iVBORw0KGgoAAAANSUhEUgAAABgAAAAYCAYAAADgdz34AAAAAXNSR0IArs4c6QAAARtJREFUSEvV1D8uRUEUBvDfQ0Kikyh1QqmVSIQNoGENdqDSSDRiATodpbAArUoUSkuwAJU/GZkr48a9zrvvXYmpJmfOfN93zndmBnpeg57xDUuwlQXdRIX9RJBi0w0ALzkeFlZPnMIDFhsIZkYhmMc9FgLld6rgEEcB8JTSiWAW59gNkHQiSLgTOMZ63te5VgsPljBXJLzhEdUgfB6FlWSg94LgCjs1Bc9Yw1MVHzdBwk0iVnI1Y6+gEn6Akz5alDAT+CmSJ60VbCIZWa6zwoP93Irq/BUXuMttajX5EnsNk/SbsG+K6iZP4jaPadtzCA/HnxNUqntrUdmWDSy3mBz4UUZ7yf+TYDvLvg7J7/DZRXG/8sLzPDRyvvABRhomGWVTQQkAAAAASUVORK5CYII=",
      "tags": [],
      "minZoom": null,
      "maxZoom": null
    },
    {
      "type": "statue",
      "iconName": "map-marker",
      "color": "#dddddd",
      "layer": true,
      "transform": {
        "size": 6,
        "x": 0,
        "y": -2
      },
      "isImage": true,
      "imageUrl": "data:image/png;base64,iVBORw0KGgoAAAANSUhEUgAAABgAAAAYCAYAAADgdz34AAAAAXNSR0IArs4c6QAAAQVJREFUSEvt1L0uhFEQgOFnRaHTSFRcgESiRbbU+rsJtAqJqCkU2uUixE+rFLQSiQugkmh0ChGZ5GyzfPZ8+51Vmeok58z75sxMpmXI0arBH0U7vb/GR05uHcE6ThM0zmelBQfYTdA475UWjCNKExGleistyOF9e1OnB/PYToQj3OUYcwUzeMBIgn5iFo/9JLmCZVz0wFZwWUqw+sNYruH8X9CtwNBLNImrNDkhjYlawkupHgSng80EPMZWP3jc547pnwh2EKMZEZv0sPQPcngD7aKxtJonerJfsY/338w5PVjATQVkEbdNBU+YqoA8Y7qpYANzFZB7nDQVDNTcblJODxoJvgD0nSkZ9DaEzgAAAABJRU5ErkJggg==",
      "tags": [],
      "minZoom": null,
      "maxZoom": null
    },
    {
      "type": "tower",
      "iconName": "map-marker",
      "color": "#dddddd",
      "layer": true,
      "transform": {
        "size": 6,
        "x": 0,
        "y": -2
      },
      "isImage": true,
      "imageUrl": "data:image/png;base64,iVBORw0KGgoAAAANSUhEUgAAABgAAAAYCAYAAADgdz34AAAAAXNSR0IArs4c6QAAARdJREFUSEvt1c8qRVEUBvDfLeaSeAlFJh7AQEjIMxgo3sE7MLjlHTDCyNhIkjyDpGRkQNHSpt3hnM6f7h3dNTrr7L2/b69/3+4ZsPUGjG/oBIfYwzsWcJ8inMUNxpO/hvP0PYkHzCT/CPs/mSlG8JmlbAtnyd/EabbWx27yF3FdSPUvbhXBLY7TwR3MZyCvOMAbIpr1NgRd6l8awQsmuiAjMKIu31ZM0RIuMdaS5APLuCojiP8bWXGb8mzjJD9UNgd5NzUh+YM3Iiimr1OKntNwBWgM2dQ/xWlN8Ig5PCXQadxl+lPalXWLfIHVwo1D7FbKJKJqDmKt2KYheiF+uYX4hQhWtn3dCEYETdSg2d6hv8nNrldj9xfV3TQZDOiv9wAAAABJRU5ErkJggg==",
      "tags": [],
      "minZoom": null,
      "maxZoom": null
    },
    {
      "type": "trail",
      "iconName": "map-marker",
      "color": "#dddddd",
      "layer": true,
      "transform": {
        "size": 6,
        "x": 0,
        "y": -2
      },
      "isImage": true,
      "imageUrl": "data:image/png;base64,iVBORw0KGgoAAAANSUhEUgAAABgAAAAYCAYAAADgdz34AAAAAXNSR0IArs4c6QAAAiZJREFUSEvV1UmojmEUB/DflVmKXEM2hhQ2iq7IUGSBtaQkCxEbUaRLkWQqFoZkYWElC8qGErGRZMiCKAuSJJlSpsw6X89bz33v+36+0l049S3ec55z/v8zfm16WNp6OL46gFFYhaP48C8k6gDeYBhuYFYJYBCuYBom4zENosvRiQ58LXzqAN5hKO5gegYwAffRH3NwPdkW4HICeoRJzQD2Y0t6/BNLcQ4j8TQFv40Z+J0CBevQhZxNPo2Pqgw24FDGOthdxXocSfpTWJG9Cfv87HsMnlUB9EWUZ2AGfgkLcQCbU5BPiCBv0Rvn05sCI0oZvemWQWS0DBOxE5FNpB7NDobBtJCTWJPqHX15jyH4hV3pVzumI7AHGxFsQwbjZcquANmB3RidslubJusFvtf1oNnYL8GZUuZB4nBiPxsX8gDlJsek3EtzvhI/Smh9Ut0jm1xiB05XMSsDRAkCJGQxLlY47UsLlZuiHDNxt/w+BwhWscExSSHbU33LPuPwpAL4dSJX7EbjSQ6wDsczx1iy8cU8Z/oB+FzTqC5LVgbYi60lxynpNOTqTThYAxDAcWK+FfY8g7gfD9ArGePOzCs1Og7g83QuqjC+JIDaYzcVN3ELi/Axi9Kelm5sDftQRw9jSGLZuvUgFP3wCsewLQsUm30Nw5sED1NsfnGvKgGq/FfjxF8ChzluT9ygLtLKX+bDtP7NMGL+51ZNVysALZCvf/L/A/wBQw1kGQnQsL4AAAAASUVORK5CYII=",
      "tags": [],
      "minZoom": null,
      "maxZoom": null
    },
    {
      "type": "volcano",
      "iconName": "map-marker",
      "color": "#dddddd",
      "layer": true,
      "transform": {
        "size": 6,
        "x": 0,
        "y": -2
      },
      "isImage": true,
      "imageUrl": "data:image/png;base64,iVBORw0KGgoAAAANSUhEUgAAABgAAAAYCAYAAADgdz34AAAAAXNSR0IArs4c6QAAAaRJREFUSEvd1T9LVmEYx/HPU2RDEJVTFJRDbRYFRhREOoqI0VJDSEPgy6jeRUuE4CRUFIQ0tKSCIkoODoKDUTkYVOBikcUlt3K4efR5zjm0dI3nnOv3vf6fhn9sjQr6Z3ABB7GOqf00ygJOYA0dSfQHjhUAg/iD1zvPygBC/BWu4xS+FIRD5yi+4xvi221rFxBlWU6RP8FIVpabmEjvr2K2LGAgRX86RR6BDeMwDuABTiLEV4vwdjOI9K+lKMP/Fp4XhDZxBy/zhrcLaOZ3GYdSUz/hc7NpagWI94sYx+NM4Ag68bHOmF7CfEo9ylK0p7iN49jaC9Iqg1HcKwD6k9AbvMAQolQLVQBnsZKmJJoXGcQShUXU0eRePMP9KoB3SSB8c8DP1OCowO90OpbKNLkPb9O9aQbItebQUwYQW3uu4JBn0EzrIR61swd3MZadkWnEIfu6z0huoCv/Jp+iWJwQic2tYjHSUardsc0BcSknqygnnxDuxm7Dc8AMrtQAhOt73NjRyAEfcL4mIAbk4l6A+A1GH+rYr7Qb2xqtTkUd0H8C+AvsZEkZUowtTQAAAABJRU5ErkJggg==",
      "tags": [],
      "minZoom": null,
      "maxZoom": null
    },
    {
      "type": "waterfall",
      "iconName": "map-marker",
      "color": "#dddddd",
      "layer": true,
      "transform": {
        "size": 6,
        "x": 0,
        "y": -2
      },
      "isImage": true,
      "imageUrl": "data:image/png;base64,iVBORw0KGgoAAAANSUhEUgAAABgAAAAYCAYAAADgdz34AAAAAXNSR0IArs4c6QAAAZ1JREFUSEu91c1LFlEUx/GPSCUuwoIwwkW0cVfQohYFgbgODIVa9IKb6IWidtU2IhQtENwVBIGCO6FlEIHgKqiU+gckiuhlE0SvnDhPDIOzGOd5vDCLuXPv73vOvb9zpkuHR1eH9W064E8ho294iFv4nk/r8zb8RA8mMY6Ya43/gZczKAJai3+k2Bie5ORXRADb0bvOMdcCxP5nGMGXFJvApQrxWFIbcBqPS5EuYLTCJLUBR7FUErud97MeozZgAMdxE/sQ93IGj9qRQYiFQ6ZxHjvSUYex3A7AO+xBH44UnBSgT+0AvMKBgtDWPKKwdNg1rFoete7gKYZTIcTXEDaNAnuLwaaAeZxKkajcz3iAy1kfx5oCZnAlRSL1IazgPeZwsingBu5WXOYUrjcFnMVi+n81LRot4w1e4GJTwD1cyM4ZttyLOLYT2Yu6mwJif5z3LM7hED5mFUc112oVH7Ard4RT7uA5orFdqxC7ivuFb6HR33ov/w924yV24iBeYwt+4XcFINZGPURgIb4/M/63fNN/mRVBbny64xn8BWeBWBmuBXjPAAAAAElFTkSuQmCC",
      "tags": [],
      "minZoom": null,
      "maxZoom": null
    },
    {
      "type": "wildlife",
      "iconName": "map-marker",
      "color": "#dddddd",
      "layer": true,
      "transform": {
        "size": 6,
        "x": 0,
        "y": -2
      },
      "isImage": true,
      "imageUrl": "data:image/png;base64,iVBORw0KGgoAAAANSUhEUgAAABgAAAAYCAYAAADgdz34AAAAAXNSR0IArs4c6QAAAnRJREFUSEvN1UvIlWUUBeDnV8tStDIJRUQHVpKQaBp5mQgJDkIJFaJJkmIJKliIJopiNCgvJRVdMEFoIGblbZJ2caADkaxB1kwKQYXCC4FamsmCrRy//yLyI/jC4RzO95611l577X3a3OHTdofxdZdgEJ6u1wBu4H2LLyO+OwTTsbMTjMV4/3YJnsDreA3n8ScGNiw+g1QyF1uaBKnmY7yEq1iHI3gTw/AQ/qn3EXgXvXEAC/E/jmEyFhTWTRaNxs8NRSG6UH7uKIDfC6z16r+ILctLzGqsbVbwFlY0CDbWxVjS1UnVW6vZPXAaEXJTBfPxSQvKeiy9zRgnUZ0S9ME2PIdTeLTsaXL0LbXD8QE+x5W6lB4kDCsRR9rFdAyOYhq+qedPIk1NtmNV4vc87q/EBCiAOd9jCl7Bpx0RbMdsPFIxfBUf4RL+wEhsxnsYX1EMaRKWFO3Hs5iHzzoiOIsHcU+V/RsGIxO7qZTFypPIe+4laakmSfoRY7GkRLSz6DJ6VaOiKOr6VTyHlCURNgG7a9A+rDnI96kss/EdEut2BBmsceiPv3G4ope7v2JUS8fvrXt/dZW05i6ahS8wE1/hKWzAOSxCwJ7BjOrFLwUeiy5iV/UvM5Gt0K6CqMqAPFxJ+qGhbir2Vn+SrMQ5gXgHc3AQk8qyWNfhNk1Tf6ofLqu4tU7yA2XNiRISryMswPsQER0uu1axAUnuY1HAV2FPWZTdFMDH8TWG4o2y8hAm3qqCVqLs/OQ5KzgroHkyHy8WUZ4dr1i/jTWdWdQE6VlWvIwX8FgNYfZWYpmKrp/76sN/SOS79Y/WVTpvPOvOX+bdQXAND6iFGfd2M4QAAAAASUVORK5CYII=",
      "tags": [],
      "minZoom": null,
      "maxZoom": null
    }
  ],
  "color": "#dddddd",
  "lat": 39.983334,
  "long": -82.98333,
  "notePreview": false,
  "layerMarkers": true,
  "previousVersion": "5.7.2",
  "version": {
    "major": 5,
    "minor": 7,
    "patch": 2
  },
  "warnedAboutMapMarker": false,
  "copyOnClick": false,
  "displayMarkerTooltips": "hover",
  "displayOverlayTooltips": false,
  "configDirectory": null,
  "mapViewEnabled": true,
  "mapViewParameters": {
    "darkMode": false,
    "defaultZoom": 7.5,
    "distanceMultiplier": 1,
    "drawColor": "#3388ff",
    "geojson": [],
    "geojsonColor": "#3388ff",
    "gpx": [],
    "gpxColor": "#3388ff",
    "height": "800px",
    "image": "[[bullionmap.png]]",
    "imageOverlay": [],
    "isMapView": false,
    "layers": [
      "[[bullionmap.png]]"
    ],
    "linksFrom": [],
    "linksTo": [],
    "marker": [],
    "commandMarker": [],
    "markerFile": [],
    "markerFolder": [],
    "markerTag": [],
    "maxZoom": 10,
    "minZoom": 5,
    "osmLayer": true,
    "overlay": [],
    "overlayColor": "blue",
    "scale": 650,
    "showAllMarkers": false,
    "tileServer": [],
    "verbose": false,
    "zoomDelta": 1,
    "zoomFeatures": false,
    "id": "leaflet-map2",
    "lat": 50,
    "long": 50,
    "unit": "kilometers",
    "filterTag": []
  },
  "enableDraw": false,
  "defaultUnitType": "metric",
  "defaultTile": "https://stamen-tiles.a.ssl.fastly.net/terrain/{z}/{x}/{y}.png",
  "defaultTileDark": "https://stamen-tiles.a.ssl.fastly.net/terrain/{z}/{x}/{y}.png",
  "defaultAttribution": "Map tiles by <a href=\"http://stamen.com\">Stamen Design</a>, under <a href=\"http://creativecommons.org/licenses/by/3.0\">CC BY 3.0</a>. Data by <a href=\"http://openstreetmap.org\">OpenStreetMap</a>, under <a href=\"http://www.openstreetmap.org/copyright\">ODbL</a>.",
  "defaultTileSubdomains": "a,b,c"
}